pretix_regex_validation/__init__.py
pretix_regex_validation/apps.py
pretix_regex_validation/signals.py
pretix_regex_validation/urls.py
pretix_regex_validation/views.py
pretix_regex_validation/locale/de/LC_MESSAGES/django.mo
pretix_regex_validation/locale/de/LC_MESSAGES/django.po
pretix_regex_validation/locale/de_Informal/.gitkeep
pretix_regex_validation/locale/de_Informal/LC_MESSAGES/django.mo
pretix_regex_validation/locale/de_Informal/LC_MESSAGES/django.po
pretix_regex_validation/static/pretix_regex_validation/.gitkeep
pretix_regex_validation/templates/pretix_regex_validation/.gitkeep
pretix_regex_validation/templates/pretix_regex_validation/settings.html
pretix_regex_validation-1.1.0.dist-info/LICENSE
pretix_regex_validation-1.1.0.dist-info/METADATA
pretix_regex_validation-1.1.0.dist-info/WHEEL
pretix_regex_validation-1.1.0.dist-info/entry_points.txt
pretix_regex_validation-1.1.0.dist-info/top_level.txt
pretix_regex_validation-1.1.0.dist-info/RECORD
