Metadata-Version: 2.1
Name: pretix-regex-validation
Version: 1.1.0
Summary: Allows to add arbitrary regex validation to fields
Home-page: https://github.com/pretix-unofficial/pretix-regex-validation
Author: pretix team
Author-email: support@pretix.eu
License: Apache
License-File: LICENSE
